pyticleswarm/PSO.py
pyticleswarm/__init__.py
pyticleswarm/res.py
pyticleswarm/run_PSO.py
Pyticle_Swarm-1.0.8.dist-info/LICENSE
Pyticle_Swarm-1.0.8.dist-info/METADATA
Pyticle_Swarm-1.0.8.dist-info/WHEEL
Pyticle_Swarm-1.0.8.dist-info/top_level.txt
Pyticle_Swarm-1.0.8.dist-info/RECORD
