Metadata-Version: 2.1
Name: Pyticle-Swarm
Version: 1.0.8
Summary: PSO library
Home-page: https://pyticle-swarm.readthedocs.io/
Author: Bruno Veiga, Ricardo Faia, Tiago Pinto, Zita Vale
Author-email: btsve@isep.ipp.com, rfmfa@isep.ipp.pt, tcp@isep.ipp.pt, zav@isep.ipp.pt
License: BSD 3-Clause
Platform: UNKNOWN
Classifier: Programming Language :: Python
Classifier: Programming Language :: Python :: 3.9
Classifier: Operating System :: OS Independent
License-File: LICENSE
Requires-Dist: numpy (==1.21.3)
Requires-Dist: matplotlib (==3.4.3)
Requires-Dist: matplotlib-inline (==0.1.3)
Requires-Dist: joblib (==1.1.0)
